mfrc522_i2c/__init__.py
mfrc522_i2c/mfrc522_i2c.py
mfrc522_i2c-0.0.5.dist-info/LICENSE
mfrc522_i2c-0.0.5.dist-info/METADATA
mfrc522_i2c-0.0.5.dist-info/WHEEL
mfrc522_i2c-0.0.5.dist-info/top_level.txt
mfrc522_i2c-0.0.5.dist-info/RECORD
